__init__.py
main.py
config/__init__.py
config/constants.py
utils/__init__.py
utils/helpers.py
utils/logs.py
utils/secretStore.py
utils/webscraping.py
plutus_mr-0.0.2.dist-info/LICENSE
plutus_mr-0.0.2.dist-info/METADATA
plutus_mr-0.0.2.dist-info/WHEEL
plutus_mr-0.0.2.dist-info/top_level.txt
plutus_mr-0.0.2.dist-info/RECORD
