Metadata-Version: 2.1
Name: plutus_mr
Version: 0.0.2
Summary: YOLO
Author-email: Rolf Lobo <rolf.lobo@trustgroup.in>
Project-URL: Homepage, https://github.com/pypa/sampleproject
Project-URL: Issues, https://github.com/pypa/sampleproject/issues
Classifier: Programming Language :: Python :: 3
Classifier: License :: OSI Approved :: GNU General Public License v3 (GPLv3)
Classifier: Operating System :: OS Independent
Requires-Python: ==3.10.13
License-File: LICENSE
